{"_type":"export","__export_format":4,"__export_date":"2021-11-18T21:38:09.092Z","__export_source":"insomnia.desktop.app:v2021.5.3","resources":[{"_id":"req_af6a5791b5da4c80a2d894e50015adf3","parentId":"wrk_871db82ff64b45569a74f3d5d9a0c197","modified":1637084903640,"created":1635339147404,"url":"{{ _.baseUrl }}/certificate","name":"produz certificado","description":"","method":"POST","body":{"mimeType":"application/json","text":"{\n\t\"name\": \"GoJava2\",\n\t\"data\": \"14/01/21\",\n\t\"participants\": [\n\t\t{\n\t\t\t\"name\": \"Alex1\",\n\t\t\t\"identifier\": \"12312312312\"\n\t\t},\n\t\t{\n\t\t\t\"name\": \"Alex2\",\n\t\t\t\"identifier\": \"12312312312\"\n\t\t},\n\t\t{\n\t\t\t\"name\": \"Alex3\",\n\t\t\t\"identifier\": \"12312312312\"\n\t\t},\n\t\t{\n\t\t\t\"name\": \"Alex4\",\n\t\t\t\"identifier\": \"12312312312\"\n\t\t},\n\t\t{\n\t\t\t\"name\": \"Alex5\",\n\t\t\t\"identifier\": \"12312312312\"\n\t\t},\n\t\t{\n\t\t\t\"name\": \"Alex6\",\n\t\t\t\"identifier\": \"12312312312\"\n\t\t},\n\t\t{\n\t\t\t\"name\": \"Alex7\",\n\t\t\t\"identifier\": \"12312312312\"\n\t\t},\n\t\t{\n\t\t\t\"name\": \"Alex8\",\n\t\t\t\"identifier\": \"12312312312\"\n\t\t},\n\t\t{\n\t\t\t\"name\": \"Alex9\",\n\t\t\t\"identifier\": \"12312312312\"\n\t\t}\n\t]\n}"},"parameters":[],"headers":[{"name":"Content-Type","value":"application/json","id":"pair_b9787f372a19479a97333cd0ad2fed6f"}],"authentication":{},"metaSortKey":-1635339147404,"isPrivate":false,"settingStoreCookies":true,"settingSendCookies":true,"settingDisableRenderRequestBody":false,"settingEncodeUrl":true,"settingRebuildPath":true,"settingFollowRedirects":"global","_type":"request"},{"_id":"wrk_871db82ff64b45569a74f3d5d9a0c197","parentId":null,"modified":1635339124809,"created":1635339124809,"name":"mensageria-test","description":"","scope":"collection","_type":"workspace"},{"_id":"req_fe7d4de86d37448da33a286363f34624","parentId":"wrk_871db82ff64b45569a74f3d5d9a0c197","modified":1637266929974,"created":1636480768212,"url":"{{ _.baseUrl }}/products","name":"cria produto","description":"","method":"POST","body":{"mimeType":"application/json","text":"{\n\t\"name\": \"teste76\"\n}"},"parameters":[],"headers":[{"name":"Content-Type","value":"application/json","id":"pair_b9787f372a19479a97333cd0ad2fed6f"}],"authentication":{"type":"basic","useISO88591":false,"disabled":false,"username":"user","password":"pass"},"metaSortKey":-1635339147354,"isPrivate":false,"settingStoreCookies":true,"settingSendCookies":true,"settingDisableRenderRequestBody":false,"settingEncodeUrl":true,"settingRebuildPath":true,"settingFollowRedirects":"global","_type":"request"},{"_id":"req_cb8dd6341e664441a6f335984f7dae4d","parentId":"wrk_871db82ff64b45569a74f3d5d9a0c197","modified":1637103230660,"created":1636480840380,"url":"{{ _.baseUrl }}/products","name":"get produto","description":"","method":"GET","body":{"mimeType":"application/json","text":""},"parameters":[],"headers":[{"name":"Content-Type","value":"application/json","id":"pair_b9787f372a19479a97333cd0ad2fed6f"}],"authentication":{"type":"basic","useISO88591":false,"disabled":false,"username":"user","password":"pass"},"metaSortKey":-1635339147304,"isPrivate":false,"settingStoreCookies":true,"settingSendCookies":true,"settingDisableRenderRequestBody":false,"settingEncodeUrl":true,"settingRebuildPath":true,"settingFollowRedirects":"global","_type":"request"},{"_id":"req_d743e3495bdb4c2db1312d85d5c09a48","parentId":"wrk_871db82ff64b45569a74f3d5d9a0c197","modified":1637260145081,"created":1637259939460,"url":"{{ _.baseUrl }}/products/logs","name":"get logs","description":"","method":"GET","body":{"mimeType":"application/json","text":""},"parameters":[],"headers":[{"name":"Content-Type","value":"application/json","id":"pair_b9787f372a19479a97333cd0ad2fed6f"}],"authentication":{"type":"basic","useISO88591":false,"disabled":false,"username":"user","password":"pass"},"metaSortKey":-1635339147254,"isPrivate":false,"settingStoreCookies":true,"settingSendCookies":true,"settingDisableRenderRequestBody":false,"settingEncodeUrl":true,"settingRebuildPath":true,"settingFollowRedirects":"global","_type":"request"},{"_id":"env_5339ea01c620ffd4adf3527bb34cac28b614f230","parentId":"wrk_871db82ff64b45569a74f3d5d9a0c197","modified":1637084938787,"created":1635339124812,"name":"Base Environment","data":{"baseUrl":"{{host}}"},"dataPropertyOrder":{"&":["baseUrl"]},"color":null,"isPrivate":false,"metaSortKey":1635339124812,"_type":"environment"},{"_id":"jar_5339ea01c620ffd4adf3527bb34cac28b614f230","parentId":"wrk_871db82ff64b45569a74f3d5d9a0c197","modified":1637271402487,"created":1635339124812,"name":"Default Jar","cookies":[{"key":"JSESSIONID","value":"98FA337D409C9CDDEAE58D0898C869BC","domain":"localhost","path":"/","httpOnly":true,"hostOnly":true,"creation":"2021-11-18T18:28:58.874Z","lastAccessed":"2021-11-18T20:49:19.609Z","id":"3526972481671211"},{"key":"JSESSIONID","value":"29694FC8C5C7D3100E588F5B59512BBB","domain":"172.20.0.2","path":"/","httpOnly":true,"hostOnly":true,"creation":"2021-11-18T21:36:42.487Z","lastAccessed":"2021-11-18T21:36:42.487Z","id":"8620773955228465"}],"_type":"cookie_jar"},{"_id":"spc_f572ee17e2a34e67b1b9dcc275e7c1d0","parentId":"wrk_871db82ff64b45569a74f3d5d9a0c197","modified":1635339124810,"created":1635339124810,"fileName":"mensageria-test","contents":"","contentType":"yaml","_type":"api_spec"},{"_id":"env_b46a6e596dc145c4bf0d238f097e9f87","parentId":"env_5339ea01c620ffd4adf3527bb34cac28b614f230","modified":1637084818575,"created":1637084717682,"name":"localhost","data":{"host":"localhost:8080"},"dataPropertyOrder":{"&":["host"]},"color":null,"isPrivate":false,"metaSortKey":1637084717682,"_type":"environment"},{"_id":"env_eed3b9cfd68a4c54811314636f9843bc","parentId":"env_5339ea01c620ffd4adf3527bb34cac28b614f230","modified":1637084766202,"created":1637084760684,"name":"docker","data":{"host":"localhost"},"dataPropertyOrder":{"&":["host"]},"color":null,"isPrivate":false,"metaSortKey":1637084717732,"_type":"environment"},{"_id":"env_7e8e5f5820784fcbaeeda709db00dd17","parentId":"env_5339ea01c620ffd4adf3527bb34cac28b614f230","modified":1637104133223,"created":1637084771530,"name":"kubernetes","data":{"host":"172.20.0.2:30001"},"dataPropertyOrder":{"&":["host"]},"color":null,"isPrivate":false,"metaSortKey":1637084717782,"_type":"environment"},{"_id":"env_2db9368eec6b44d89a75ec3aefa758da","parentId":"env_5339ea01c620ffd4adf3527bb34cac28b614f230","modified":1637101956819,"created":1637085671314,"name":"kubernetes (8080)","data":{"host":"localhost:8080"},"dataPropertyOrder":{"&":["host"]},"color":null,"isPrivate":false,"metaSortKey":1637084717832,"_type":"environment"},{"_id":"env_95636c7a6cd44aa2af5ec3eb01c91091","parentId":"env_5339ea01c620ffd4adf3527bb34cac28b614f230","modified":1637102049022,"created":1637102021808,"name":"kubernetes (80)","data":{"host":"localhost"},"dataPropertyOrder":{"&":["host"]},"color":null,"isPrivate":false,"metaSortKey":1637084717882,"_type":"environment"}]}